django_polls_tutorial_v-1.2.6.data/scripts/docs_app
docs/__init__.py
docs/settings.py
docs/test_settings.py
docs/urls.py
docs/wsgi.py
polls/__init__.py
polls/admin.py
polls/apps.py
polls/models.py
polls/tests.py
polls/urls.py
polls/views.py
polls/migrations/0001_initial.py
polls/migrations/__init__.py
polls/static/polls/style.css
polls/static/polls/images/background.gif
polls/templates/polls/detail.html
polls/templates/polls/index.html
polls/templates/polls/results.html
django_polls_tutorial_v-1.2.6.dist-info/LICENSE
django_polls_tutorial_v-1.2.6.dist-info/METADATA
django_polls_tutorial_v-1.2.6.dist-info/WHEEL
django_polls_tutorial_v-1.2.6.dist-info/top_level.txt
django_polls_tutorial_v-1.2.6.dist-info/RECORD
