Metadata-Version: 2.1
Name: django-polls-tutorial-v
Version: 1.2.6
Summary: A simple Django app to conduct Web-based polls.
Home-page: UNKNOWN
Author: kevin
Author-email: kevin@kev.com
License: BSD License
Platform: UNKNOWN
Classifier: Environment :: Web Environment
Classifier: Framework :: Django
Classifier: Framework :: Django :: 2.1
Classifier: Intended Audience :: Developers
Classifier: License :: OSI Approved :: BSD License
Requires-Dist: Django (==2.2.2)
Requires-Dist: django-nose (==1.4.6)
Requires-Dist: pytest-django (==3.5.0)
Requires-Dist: django-pytest (==0.2.0)
